testplay/__init__.py
testplay/functionality/__init__.py
testplay/functionality/functionality.py
testplay/other_functionality/__init__.py
testplay/other_functionality/other_functionality.py
testplay-0.0.4.dist-info/METADATA
testplay-0.0.4.dist-info/WHEEL
testplay-0.0.4.dist-info/licence.md
testplay-0.0.4.dist-info/top_level.txt
testplay-0.0.4.dist-info/RECORD
