Metadata-Version: 2.1
Name: testplay
Version: 0.0.4
Summary: Just playing around
Author: Darsh (Subhash Mishra)
Author-email: subhashmishra4322@gmail.com
Classifier: Development Status :: 1 - Planning
Classifier: Intended Audience :: Developers
Classifier: Programming Language :: Python :: 3
Classifier: Operating System :: Unix
Classifier: Operating System :: MacOS :: MacOS X
Classifier: Operating System :: Microsoft :: Windows
License-File: licence.md
